delta/alembic/README
delta/alembic/env.py
delta/alembic/script.py.mako
delta/alembic/versions/1ec1eabe45bf_update_run_status_enum.py
delta/alembic/versions/24bd81ed7dad_add_parent_run_column_in_run_table.py
delta/alembic/versions/2e57fc6dd873_update_run_table.py
delta/alembic/versions/825d896d998a_database_creation.py
delta/alembic/versions/a2bfaf2e8406_add_secret_value_column_to_parameters.py
delta/core/__init__.py
delta/core/_version.py
delta/core/delta_core.py
delta/drive/__init__.py
delta/drive/delta_drive.py
delta/drive/interfaces/__init__.py
delta/drive/interfaces/i_drive.py
delta/exceptions/runners/__init__.py
delta/manifest/README.md
delta/manifest/__init__.py
delta/manifest/constants.py
delta/manifest/manifest.py
delta/manifest/models.py
delta/manifest/parser.py
delta/manifest/v1_0/__init__.py
delta/manifest/v1_0/manifest-schema.json
delta/manifest/v1_0/minimum.json
delta/manifest/v1_1/__init__.py
delta/manifest/v1_1/manifest-schema.json
delta/manifest/v1_1/minimum.json
delta/manifest/v1_2/__init__.py
delta/manifest/v1_2/manifest-schema.json
delta/manifest/v1_2/minimum.json
delta/manifest/v1_3/__init__.py
delta/manifest/v1_3/manifest-schema.json
delta/manifest/v1_3/minimum.json
delta/manifest/v1_4/__init__.py
delta/manifest/v1_4/manifest-schema.json
delta/manifest/v1_4/minimum.json
delta/run/__init__.py
delta/run/config.py
delta/run/orchestrator.py
delta/run/storage_manager.py
delta/run/utils.py
delta/run/api/__init__.py
delta/run/api/model.py
delta/run/db/__init__.py
delta/run/db/daos.py
delta/run/db/database.py
delta/run/db/orm.py
delta/run/job/__init__.py
delta/run/job/docker_service.py
delta/run/job/builder/__init__.py
delta/run/job/builder/python_builder.py
delta/runners/factory.py
delta/runners/run.py
delta_core-1.2.7.dist-info/METADATA
delta_core-1.2.7.dist-info/WHEEL
delta_core-1.2.7.dist-info/top_level.txt
delta_core-1.2.7.dist-info/RECORD
