Metadata-Version: 2.4
Name: delta-core
Version: 1.2.7
Summary: Delta core
Classifier: License :: OSI Approved :: GNU Lesser General Public License v3 (LGPLv3)
Requires-Python: ~=3.11
Requires-Dist: requests>=2.27.0
Requires-Dist: jsonschema>=4.17.0
Requires-Dist: s3fs==2023.12.2
Requires-Dist: pydantic==2.5.3
Requires-Dist: pydantic-settings==2.2.1
Requires-Dist: fastapi==0.109.2
Requires-Dist: uvicorn==0.25.0
Requires-Dist: sqlalchemy==2.0.25
Requires-Dist: alembic==1.13.1
Requires-Dist: boto3==1.34.51
Requires-Dist: apscheduler==3.10.4
Requires-Dist: pytz==2024.1
Requires-Dist: docker>=7.0.0
Requires-Dist: psycopg[binary,pool]==3.1.18
Requires-Dist: python-jose==3.3.0
Requires-Dist: redis==5.0.6
Requires-Dist: python-socketio==5.11.2
Requires-Dist: rsa==4.9
Requires-Dist: aiohttp==3.9.5
Requires-Dist: greenlet<3.2
Requires-Dist: packaging==25.0
Requires-Dist: pyyaml==6.0.3
